{
  "script": "phase1_approval.py",
  "version": "0.5.6",
  "run_id": "20251208_041158",
  "best_acc": 0.9675,
  "final_trust": 0.9933071732521057,
  "final_internalization": 0.9933071732521057,
  "epochs_completed": 10,
  "curriculum_topics": [
    "alternating",
    "repeating",
    "incrementing",
    "fixed_offset",
    "periodic_repeat"
  ],
  "args": {
    "data_dir": "data",
    "n_train": 20000,
    "n_val": 2000,
    "batch_size": 64,
    "lr": 0.001,
    "epochs": 10,
    "d_model": 64,
    "n_heads": 4,
    "n_think_steps": 5
  },
  "history": [
    {
      "epoch": 1,
      "train_acc": 0.4387,
      "train_loss": 1.8932337459564208,
      "val_acc": 0.635,
      "show_rate": 0.0426,
      "approval_rate": 1.0,
      "show_reasons": {
        "creative": 0,
        "streak": 6,
        "validation": 845,
        "spontaneous": 1
      },
      "internalization": 0.9933071732521057,
      "trust": 0.9933071732521057,
      "show_calibration": 0.9999997615814209,
      "per_pattern": {
        "alternating": 0.5,
        "repeating": 1.0,
        "incrementing": 0.6352040816326531,
        "fixed_offset": 0.6077481840193705,
        "periodic_repeat": 0.39893617021276595
      },
      "teacher_goal": 15,
      "student_goal_estimate": 3.0,
      "teacher_impressedness": 0.6000000238418579,
      "goal_calibration_rate": 0.5,
      "topic_calibration": {
        "alternating": {
          "accuracy": 0.5423431992530823,
          "confidence": 0.594062328338623,
          "gap": -0.05171912908554077,
          "status": "calibrated",
          "streak": 1,
          "best_streak": 9,
          "mastered": false,
          "xp": 10.0,
          "level": 1,
          "level_progress": 0.0,
          "xp_high": 10.0
        },
        "repeating": {
          "accuracy": 0.9999997615814209,
          "confidence": 0.6179440021514893,
          "gap": 0.38205575942993164,
          "status": "guessing",
          "streak": 778,
          "best_streak": 1405,
          "mastered": true,
          "xp": 10.0,
          "level": 1,
          "level_progress": 0.0,
          "xp_high": 10.0
        },
        "incrementing": {
          "accuracy": 0.608171284198761,
          "confidence": 0.5956095457077026,
          "gap": 0.01256173849105835,
          "status": "calibrated",
          "streak": 0,
          "best_streak": 16,
          "mastered": false,
          "xp": 10.0,
          "level": 1,
          "level_progress": 0.0,
          "xp_high": 10.0
        },
        "fixed_offset": {
          "accuracy": 0.4348146617412567,
          "confidence": 0.6062511801719666,
          "gap": -0.17143651843070984,
          "status": "overconfident",
          "streak": 0,
          "best_streak": 14,
          "mastered": false,
          "xp": 10.0,
          "level": 1,
          "level_progress": 0.0,
          "xp_high": 10.0
        },
        "periodic_repeat": {
          "accuracy": 0.35816383361816406,
          "confidence": 0.5779681205749512,
          "gap": -0.2198042869567871,
          "status": "overconfident",
          "streak": 1,
          "best_streak": 8,
          "mastered": false,
          "xp": 10.0,
          "level": 1,
          "level_progress": 0.0,
          "xp_high": 10.0
        }
      },
      "total_xp": 50.0,
      "avg_level": 1.0,
      "exams": [
        {
          "passed": false,
          "score": 0.5,
          "threshold": 0.75,
          "new_level": 0,
          "xp_lost": 2.5,
          "cooldown": 1,
          "graduated": false,
          "topic": "alternating",
          "target_level": 2
        },
        {
          "passed": true,
          "score": 1.0,
          "threshold": 0.75,
          "new_level": 1,
          "xp_lost": 0.0,
          "cooldown": 0,
          "graduated": false,
          "topic": "repeating",
          "target_level": 2
        },
        {
          "passed": true,
          "score": 0.75,
          "threshold": 0.75,
          "new_level": 1,
          "xp_lost": 0.0,
          "cooldown": 0,
          "graduated": false,
          "topic": "incrementing",
          "target_level": 2
        },
        {
          "passed": false,
          "score": 0.5,
          "threshold": 0.75,
          "new_level": 0,
          "xp_lost": 2.5,
          "cooldown": 1,
          "graduated": false,
          "topic": "fixed_offset",
          "target_level": 2
        },
        {
          "passed": false,
          "score": 0.25,
          "threshold": 0.75,
          "new_level": 0,
          "xp_lost": 2.5,
          "cooldown": 1,
          "graduated": false,
          "topic": "periodic_repeat",
          "target_level": 2
        }
      ]
    },
    {
      "epoch": 2,
      "train_acc": 0.7586,
      "train_loss": 0.8472617709159851,
      "val_acc": 0.8695,
      "show_rate": 0.1512,
      "approval_rate": 1.0,
      "show_reasons": {
        "creative": 3008,
        "streak": 16,
        "validation": 0,
        "spontaneous": 0
      },
      "internalization": 0.9933071732521057,
      "trust": 0.9933071732521057,
      "show_calibration": 0.9999997615814209,
      "per_pattern": {
        "alternating": 0.8417085427135679,
        "repeating": 1.0,
        "incrementing": 0.9872448979591837,
        "fixed_offset": 0.9394673123486683,
        "periodic_repeat": 0.5531914893617021
      },
      "teacher_goal": 37,
      "student_goal_estimate": 3.0,
      "teacher_impressedness": 1.0,
      "goal_calibration_rate": 0.5,
      "topic_calibration": {
        "alternating": {
          "accuracy": 0.7484006881713867,
          "confidence": 0.8276804685592651,
          "gap": -0.07927978038787842,
          "status": "calibrated",
          "streak": 1,
          "best_streak": 29,
          "mastered": false,
          "xp": 10.0,
          "level": 1,
          "level_progress": 0.0,
          "xp_high": 10.0
        },
        "repeating": {
          "accuracy": 0.9999997615814209,
          "confidence": 0.8499053716659546,
          "gap": 0.1500943899154663,
          "status": "guessing",
          "streak": 4771,
          "best_streak": 4771,
          "mastered": true,
          "xp": 40.0,
          "level": 2,
          "level_progress": 0.0,
          "xp_high": 40.0
        },
        "incrementing": {
          "accuracy": 0.9632173180580139,
          "confidence": 0.8525594472885132,
          "gap": 0.11065787076950073,
          "status": "guessing",
          "streak": 18,
          "best_streak": 40,
          "mastered": false,
          "xp": 40.0,
          "level": 2,
          "level_progress": 0.0,
          "xp_high": 40.0
        },
        "fixed_offset": {
          "accuracy": 0.9673568606376648,
          "confidence": 0.8634775876998901,
          "gap": 0.10387927293777466,
          "status": "guessing",
          "streak": 12,
          "best_streak": 40,
          "mastered": false,
          "xp": 10.0,
          "level": 1,
          "level_progress": 0.0,
          "xp_high": 10.0
        },
        "periodic_repeat": {
          "accuracy": 0.6462211608886719,
          "confidence": 0.7446352243423462,
          "gap": -0.09841406345367432,
          "status": "calibrated",
          "streak": 0,
          "best_streak": 12,
          "mastered": false,
          "xp": 10.0,
          "level": 1,
          "level_progress": 0.0,
          "xp_high": 10.0
        }
      },
      "total_xp": 110.0,
      "avg_level": 1.399999976158142,
      "exams": [
        {
          "passed": true,
          "score": 0.75,
          "threshold": 0.75,
          "new_level": 1,
          "xp_lost": 0.0,
          "cooldown": 0,
          "graduated": false,
          "topic": "alternating",
          "target_level": 2
        },
        {
          "passed": true,
          "score": 1.0,
          "threshold": 0.75,
          "new_level": 2,
          "xp_lost": 0.0,
          "cooldown": 0,
          "graduated": false,
          "topic": "repeating",
          "target_level": 3
        },
        {
          "passed": true,
          "score": 1.0,
          "threshold": 0.75,
          "new_level": 2,
          "xp_lost": 0.0,
          "cooldown": 0,
          "graduated": false,
          "topic": "incrementing",
          "target_level": 3
        },
        {
          "passed": true,
          "score": 1.0,
          "threshold": 0.75,
          "new_level": 1,
          "xp_lost": 0.0,
          "cooldown": 0,
          "graduated": false,
          "topic": "fixed_offset",
          "target_level": 2
        },
        {
          "passed": true,
          "score": 0.75,
          "threshold": 0.75,
          "new_level": 1,
          "xp_lost": 0.0,
          "cooldown": 0,
          "graduated": false,
          "topic": "periodic_repeat",
          "target_level": 2
        }
      ]
    },
    {
      "epoch": 3,
      "train_acc": 0.8745,
      "train_loss": 0.4530501126766205,
      "val_acc": 0.8965,
      "show_rate": 0.35045,
      "approval_rate": 1.0,
      "show_reasons": {
        "creative": 6992,
        "streak": 17,
        "validation": 0,
        "spontaneous": 0
      },
      "internalization": 0.9933071732521057,
      "trust": 0.9933071732521057,
      "show_calibration": 0.9999997615814209,
      "per_pattern": {
        "alternating": 0.9221105527638191,
        "repeating": 0.9881235154394299,
        "incrementing": 1.0,
        "fixed_offset": 0.9661016949152542,
        "periodic_repeat": 0.5824468085106383
      },
      "teacher_goal": 37,
      "student_goal_estimate": 25.85887908935547,
      "teacher_impressedness": 1.0,
      "goal_calibration_rate": 0.0,
      "topic_calibration": {
        "alternating": {
          "accuracy": 0.9466670751571655,
          "confidence": 0.8541700839996338,
          "gap": 0.09249699115753174,
          "status": "calibrated",
          "streak": 15,
          "best_streak": 56,
          "mastered": false,
          "xp": 40.0,
          "level": 2,
          "level_progress": 0.0,
          "xp_high": 40.0
        },
        "repeating": {
          "accuracy": 0.9999997615814209,
          "confidence": 0.9104909896850586,
          "gap": 0.0895087718963623,
          "status": "calibrated",
          "streak": 2669,
          "best_streak": 6068,
          "mastered": true,
          "xp": 90.0,
          "level": 3,
          "level_progress": 0.0,
          "xp_high": 90.0
        },
        "incrementing": {
          "accuracy": 0.9956724047660828,
          "confidence": 0.9646879434585571,
          "gap": 0.030984461307525635,
          "status": "calibrated",
          "streak": 37,
          "best_streak": 144,
          "mastered": true,
          "xp": 90.0,
          "level": 3,
          "level_progress": 0.0,
          "xp_high": 90.0
        },
        "fixed_offset": {
          "accuracy": 0.9396448135375977,
          "confidence": 0.9366552233695984,
          "gap": 0.0029895901679992676,
          "status": "calibrated",
          "streak": 10,
          "best_streak": 102,
          "mastered": true,
          "xp": 40.0,
          "level": 2,
          "level_progress": 0.0,
          "xp_high": 40.0
        },
        "periodic_repeat": {
          "accuracy": 0.5815128684043884,
          "confidence": 0.731015145778656,
          "gap": -0.14950227737426758,
          "status": "overconfident",
          "streak": 0,
          "best_streak": 22,
          "mastered": false,
          "xp": 40.0,
          "level": 2,
          "level_progress": 0.0,
          "xp_high": 40.0
        }
      },
      "total_xp": 300.0,
      "avg_level": 2.4000000953674316,
      "exams": [
        {
          "passed": true,
          "score": 1.0,
          "threshold": 0.75,
          "new_level": 2,
          "xp_lost": 0.0,
          "cooldown": 0,
          "graduated": false,
          "topic": "alternating",
          "target_level": 3
        },
        {
          "passed": true,
          "score": 1.0,
          "threshold": 0.75,
          "new_level": 3,
          "xp_lost": 0.0,
          "cooldown": 0,
          "graduated": false,
          "topic": "repeating",
          "target_level": 4
        },
        {
          "passed": true,
          "score": 1.0,
          "threshold": 0.75,
          "new_level": 3,
          "xp_lost": 0.0,
          "cooldown": 0,
          "graduated": false,
          "topic": "incrementing",
          "target_level": 4
        },
        {
          "passed": true,
          "score": 1.0,
          "threshold": 0.75,
          "new_level": 2,
          "xp_lost": 0.0,
          "cooldown": 0,
          "graduated": false,
          "topic": "fixed_offset",
          "target_level": 3
        },
        {
          "passed": false,
          "score": 0.5,
          "threshold": 0.75,
          "new_level": 1,
          "xp_lost": 7.5,
          "cooldown": 2,
          "graduated": false,
          "topic": "periodic_repeat",
          "target_level": 3
        }
      ]
    },
    {
      "epoch": 4,
      "train_acc": 0.89955,
      "train_loss": 0.3380842230796814,
      "val_acc": 0.9125,
      "show_rate": 0.37485,
      "approval_rate": 1.0,
      "show_reasons": {
        "creative": 7457,
        "streak": 40,
        "validation": 0,
        "spontaneous": 0
      },
      "internalization": 0.9933071732521057,
      "trust": 0.9933071732521057,
      "show_calibration": 0.9999997615814209,
      "per_pattern": {
        "alternating": 0.9020100502512562,
        "repeating": 1.0,
        "incrementing": 1.0,
        "fixed_offset": 0.9951573849878934,
        "periodic_repeat": 0.6436170212765957
      },
      "teacher_goal": 36,
      "student_goal_estimate": 35.5380859375,
      "teacher_impressedness": 1.0,
      "goal_calibration_rate": 0.3157894736842105,
      "topic_calibration": {
        "alternating": {
          "accuracy": 0.978081226348877,
          "confidence": 0.8456969261169434,
          "gap": 0.1323843002319336,
          "status": "guessing",
          "streak": 17,
          "best_streak": 56,
          "mastered": false,
          "xp": 90.0,
          "level": 3,
          "level_progress": 0.0,
          "xp_high": 90.0
        },
        "repeating": {
          "accuracy": 0.9999997615814209,
          "confidence": 0.9596107006072998,
          "gap": 0.040389060974121094,
          "status": "calibrated",
          "streak": 1233,
          "best_streak": 6068,
          "mastered": true,
          "xp": 160.0,
          "level": 4,
          "level_progress": 0.0,
          "xp_high": 160.0
        },
        "incrementing": {
          "accuracy": 0.9609197974205017,
          "confidence": 0.9585607051849365,
          "gap": 0.0023590922355651855,
          "status": "calibrated",
          "streak": 9,
          "best_streak": 284,
          "mastered": true,
          "xp": 160.0,
          "level": 4,
          "level_progress": 0.0,
          "xp_high": 160.0
        },
        "fixed_offset": {
          "accuracy": 0.9999715685844421,
          "confidence": 0.9622831344604492,
          "gap": 0.03768843412399292,
          "status": "calibrated",
          "streak": 78,
          "best_streak": 176,
          "mastered": true,
          "xp": 90.0,
          "level": 3,
          "level_progress": 0.0,
          "xp_high": 90.0
        },
        "periodic_repeat": {
          "accuracy": 0.4995182752609253,
          "confidence": 0.6931283473968506,
          "gap": -0.1936100721359253,
          "status": "overconfident",
          "streak": 0,
          "best_streak": 22,
          "mastered": false,
          "xp": 40.0,
          "level": 2,
          "level_progress": 0.0,
          "xp_high": 40.0
        }
      },
      "total_xp": 540.0,
      "avg_level": 3.200000047683716,
      "exams": [
        {
          "passed": true,
          "score": 0.875,
          "threshold": 0.75,
          "new_level": 3,
          "xp_lost": 0.0,
          "cooldown": 0,
          "graduated": false,
          "topic": "alternating",
          "target_level": 4
        },
        {
          "passed": true,
          "score": 1.0,
          "threshold": 0.8,
          "new_level": 4,
          "xp_lost": 0.0,
          "cooldown": 0,
          "graduated": false,
          "topic": "repeating",
          "target_level": 5
        },
        {
          "passed": true,
          "score": 1.0,
          "threshold": 0.8,
          "new_level": 4,
          "xp_lost": 0.0,
          "cooldown": 0,
          "graduated": false,
          "topic": "incrementing",
          "target_level": 5
        },
        {
          "passed": true,
          "score": 1.0,
          "threshold": 0.75,
          "new_level": 3,
          "xp_lost": 0.0,
          "cooldown": 0,
          "graduated": false,
          "topic": "fixed_offset",
          "target_level": 4
        }
      ]
    },
    {
      "epoch": 5,
      "train_acc": 0.913,
      "train_loss": 0.2806218198299408,
      "val_acc": 0.9195,
      "show_rate": 0.39865,
      "approval_rate": 1.0,
      "show_reasons": {
        "creative": 7917,
        "streak": 56,
        "validation": 0,
        "spontaneous": 0
      },
      "internalization": 0.9933071732521057,
      "trust": 0.9933071732521057,
      "show_calibration": 0.9999997615814209,
      "per_pattern": {
        "alternating": 0.9120603015075377,
        "repeating": 1.0,
        "incrementing": 1.0,
        "fixed_offset": 1.0,
        "periodic_repeat": 0.6648936170212766
      },
      "teacher_goal": 36,
      "student_goal_estimate": 35.930667877197266,
      "teacher_impressedness": 1.0,
      "goal_calibration_rate": 0.6486486486486487,
      "topic_calibration": {
        "alternating": {
          "accuracy": 0.902394711971283,
          "confidence": 0.8562131524085999,
          "gap": 0.046181559562683105,
          "status": "calibrated",
          "streak": 8,
          "best_streak": 79,
          "mastered": false,
          "xp": 160.0,
          "level": 4,
          "level_progress": 0.0,
          "xp_high": 160.0
        },
        "repeating": {
          "accuracy": 0.9999997615814209,
          "confidence": 0.9749718308448792,
          "gap": 0.025027930736541748,
          "status": "calibrated",
          "streak": 5226,
          "best_streak": 6068,
          "mastered": true,
          "xp": 250.0,
          "level": 5,
          "level_progress": 0.0,
          "xp_high": 250.0
        },
        "incrementing": {
          "accuracy": 0.969559907913208,
          "confidence": 0.976330578327179,
          "gap": -0.006770670413970947,
          "status": "calibrated",
          "streak": 15,
          "best_streak": 350,
          "mastered": true,
          "xp": 250.0,
          "level": 5,
          "level_progress": 0.0,
          "xp_high": 250.0
        },
        "fixed_offset": {
          "accuracy": 0.9083468914031982,
          "confidence": 0.9676998257637024,
          "gap": -0.05935293436050415,
          "status": "calibrated",
          "streak": 1,
          "best_streak": 176,
          "mastered": true,
          "xp": 160.0,
          "level": 4,
          "level_progress": 0.0,
          "xp_high": 160.0
        },
        "periodic_repeat": {
          "accuracy": 0.7081425786018372,
          "confidence": 0.7495769262313843,
          "gap": -0.04143434762954712,
          "status": "calibrated",
          "streak": 1,
          "best_streak": 22,
          "mastered": false,
          "xp": 40.0,
          "level": 2,
          "level_progress": 0.0,
          "xp_high": 40.0
        }
      },
      "total_xp": 860.0,
      "avg_level": 4.0,
      "exams": [
        {
          "passed": true,
          "score": 0.875,
          "threshold": 0.8,
          "new_level": 4,
          "xp_lost": 0.0,
          "cooldown": 0,
          "graduated": false,
          "topic": "alternating",
          "target_level": 5
        },
        {
          "passed": true,
          "score": 1.0,
          "threshold": 0.8,
          "new_level": 5,
          "xp_lost": 0.0,
          "cooldown": 0,
          "graduated": false,
          "topic": "repeating",
          "target_level": 6
        },
        {
          "passed": true,
          "score": 1.0,
          "threshold": 0.8,
          "new_level": 5,
          "xp_lost": 0.0,
          "cooldown": 0,
          "graduated": false,
          "topic": "incrementing",
          "target_level": 6
        },
        {
          "passed": true,
          "score": 1.0,
          "threshold": 0.8,
          "new_level": 4,
          "xp_lost": 0.0,
          "cooldown": 0,
          "graduated": false,
          "topic": "fixed_offset",
          "target_level": 5
        },
        {
          "passed": false,
          "score": 0.625,
          "threshold": 0.75,
          "new_level": 1,
          "xp_lost": 7.5,
          "cooldown": 2,
          "graduated": false,
          "topic": "periodic_repeat",
          "target_level": 3
        }
      ]
    },
    {
      "epoch": 6,
      "train_acc": 0.9313,
      "train_loss": 0.22163147282600404,
      "val_acc": 0.934,
      "show_rate": 0.41685,
      "approval_rate": 1.0,
      "show_reasons": {
        "creative": 8218,
        "streak": 119,
        "validation": 0,
        "spontaneous": 0
      },
      "internalization": 0.9933071732521057,
      "trust": 0.9933071732521057,
      "show_calibration": 0.9999997615814209,
      "per_pattern": {
        "alternating": 0.964824120603015,
        "repeating": 1.0,
        "incrementing": 1.0,
        "fixed_offset": 0.9903147699757869,
        "periodic_repeat": 0.6968085106382979
      },
      "teacher_goal": 36,
      "student_goal_estimate": 35.99897384643555,
      "teacher_impressedness": 1.0,
      "goal_calibration_rate": 0.8311688311688312,
      "topic_calibration": {
        "alternating": {
          "accuracy": 0.9608345627784729,
          "confidence": 0.934678316116333,
          "gap": 0.026156246662139893,
          "status": "calibrated",
          "streak": 9,
          "best_streak": 86,
          "mastered": false,
          "xp": 250.0,
          "level": 5,
          "level_progress": 0.0,
          "xp_high": 250.0
        },
        "repeating": {
          "accuracy": 0.9999997615814209,
          "confidence": 0.9831085801124573,
          "gap": 0.016891181468963623,
          "status": "calibrated",
          "streak": 9219,
          "best_streak": 9219,
          "mastered": true,
          "xp": 360.0,
          "level": 6,
          "level_progress": 0.0,
          "xp_high": 360.0
        },
        "incrementing": {
          "accuracy": 0.9099997282028198,
          "confidence": 0.9783693552017212,
          "gap": -0.06836962699890137,
          "status": "calibrated",
          "streak": 1,
          "best_streak": 566,
          "mastered": true,
          "xp": 360.0,
          "level": 6,
          "level_progress": 0.0,
          "xp_high": 360.0
        },
        "fixed_offset": {
          "accuracy": 0.9987887740135193,
          "confidence": 0.9803860783576965,
          "gap": 0.018402695655822754,
          "status": "calibrated",
          "streak": 42,
          "best_streak": 537,
          "mastered": true,
          "xp": 250.0,
          "level": 5,
          "level_progress": 0.0,
          "xp_high": 250.0
        },
        "periodic_repeat": {
          "accuracy": 0.6850319504737854,
          "confidence": 0.7544652819633484,
          "gap": -0.06943333148956299,
          "status": "calibrated",
          "streak": 0,
          "best_streak": 24,
          "mastered": false,
          "xp": 40.0,
          "level": 2,
          "level_progress": 0.0,
          "xp_high": 40.0
        }
      },
      "total_xp": 1260.0,
      "avg_level": 4.800000190734863,
      "exams": [
        {
          "passed": true,
          "score": 0.9375,
          "threshold": 0.8,
          "new_level": 5,
          "xp_lost": 0.0,
          "cooldown": 0,
          "graduated": false,
          "topic": "alternating",
          "target_level": 6
        },
        {
          "passed": true,
          "score": 1.0,
          "threshold": 0.8,
          "new_level": 6,
          "xp_lost": 0.0,
          "cooldown": 0,
          "graduated": false,
          "topic": "repeating",
          "target_level": 7
        },
        {
          "passed": true,
          "score": 1.0,
          "threshold": 0.8,
          "new_level": 6,
          "xp_lost": 0.0,
          "cooldown": 0,
          "graduated": false,
          "topic": "incrementing",
          "target_level": 7
        },
        {
          "passed": true,
          "score": 0.9375,
          "threshold": 0.8,
          "new_level": 5,
          "xp_lost": 0.0,
          "cooldown": 0,
          "graduated": false,
          "topic": "fixed_offset",
          "target_level": 6
        }
      ]
    },
    {
      "epoch": 7,
      "train_acc": 0.9403,
      "train_loss": 0.18257232564687728,
      "val_acc": 0.954,
      "show_rate": 0.43585,
      "approval_rate": 1.0,
      "show_reasons": {
        "creative": 8583,
        "streak": 134,
        "validation": 0,
        "spontaneous": 0
      },
      "internalization": 0.9933071732521057,
      "trust": 0.9933071732521057,
      "show_calibration": 0.9999997615814209,
      "per_pattern": {
        "alternating": 0.964824120603015,
        "repeating": 1.0,
        "incrementing": 1.0,
        "fixed_offset": 1.0,
        "periodic_repeat": 0.7925531914893617
      },
      "teacher_goal": 36,
      "student_goal_estimate": 35.99998474121094,
      "teacher_impressedness": 1.0,
      "goal_calibration_rate": 0.8934426229508197,
      "topic_calibration": {
        "alternating": {
          "accuracy": 0.9539005756378174,
          "confidence": 0.9377068877220154,
          "gap": 0.016193687915802002,
          "status": "calibrated",
          "streak": 12,
          "best_streak": 101,
          "mastered": true,
          "xp": 360.0,
          "level": 6,
          "level_progress": 0.0,
          "xp_high": 360.0
        },
        "repeating": {
          "accuracy": 0.9999997615814209,
          "confidence": 0.9928515553474426,
          "gap": 0.0071482062339782715,
          "status": "calibrated",
          "streak": 2157,
          "best_streak": 10495,
          "mastered": true,
          "xp": 490.0,
          "level": 7,
          "level_progress": 0.0,
          "xp_high": 490.0
        },
        "incrementing": {
          "accuracy": 0.8486610054969788,
          "confidence": 0.9754239320755005,
          "gap": -0.12676292657852173,
          "status": "overconfident",
          "streak": 2,
          "best_streak": 727,
          "mastered": true,
          "xp": 490.0,
          "level": 7,
          "level_progress": 0.0,
          "xp_high": 490.0
        },
        "fixed_offset": {
          "accuracy": 0.9289537668228149,
          "confidence": 0.942767322063446,
          "gap": -0.013813555240631104,
          "status": "calibrated",
          "streak": 5,
          "best_streak": 537,
          "mastered": true,
          "xp": 360.0,
          "level": 6,
          "level_progress": 0.0,
          "xp_high": 360.0
        },
        "periodic_repeat": {
          "accuracy": 0.7571839094161987,
          "confidence": 0.8483666777610779,
          "gap": -0.09118276834487915,
          "status": "calibrated",
          "streak": 4,
          "best_streak": 29,
          "mastered": false,
          "xp": 40.0,
          "level": 2,
          "level_progress": 0.0,
          "xp_high": 40.0
        }
      },
      "total_xp": 1740.0,
      "avg_level": 5.599999904632568,
      "exams": [
        {
          "passed": true,
          "score": 0.90625,
          "threshold": 0.8,
          "new_level": 6,
          "xp_lost": 0.0,
          "cooldown": 0,
          "graduated": false,
          "topic": "alternating",
          "target_level": 7
        },
        {
          "passed": true,
          "score": 1.0,
          "threshold": 0.85,
          "new_level": 7,
          "xp_lost": 0.0,
          "cooldown": 0,
          "graduated": false,
          "topic": "repeating",
          "target_level": 8
        },
        {
          "passed": true,
          "score": 1.0,
          "threshold": 0.85,
          "new_level": 7,
          "xp_lost": 0.0,
          "cooldown": 0,
          "graduated": false,
          "topic": "incrementing",
          "target_level": 8
        },
        {
          "passed": true,
          "score": 1.0,
          "threshold": 0.8,
          "new_level": 6,
          "xp_lost": 0.0,
          "cooldown": 0,
          "graduated": false,
          "topic": "fixed_offset",
          "target_level": 7
        },
        {
          "passed": true,
          "score": 0.875,
          "threshold": 0.75,
          "new_level": 2,
          "xp_lost": 0.0,
          "cooldown": 0,
          "graduated": false,
          "topic": "periodic_repeat",
          "target_level": 3
        }
      ]
    },
    {
      "epoch": 8,
      "train_acc": 0.94695,
      "train_loss": 0.16539750061631203,
      "val_acc": 0.957,
      "show_rate": 0.4501,
      "approval_rate": 1.0,
      "show_reasons": {
        "creative": 8820,
        "streak": 182,
        "validation": 0,
        "spontaneous": 0
      },
      "internalization": 0.9933071732521057,
      "trust": 0.9933071732521057,
      "show_calibration": 0.9999997615814209,
      "per_pattern": {
        "alternating": 0.964824120603015,
        "repeating": 1.0,
        "incrementing": 1.0,
        "fixed_offset": 1.0,
        "periodic_repeat": 0.8085106382978723
      },
      "teacher_goal": 36,
      "student_goal_estimate": 35.99998474121094,
      "teacher_impressedness": 1.0,
      "goal_calibration_rate": 0.9285714285714286,
      "topic_calibration": {
        "alternating": {
          "accuracy": 0.9296169877052307,
          "confidence": 0.9166049361228943,
          "gap": 0.013012051582336426,
          "status": "calibrated",
          "streak": 4,
          "best_streak": 101,
          "mastered": true,
          "xp": 490.0,
          "level": 7,
          "level_progress": 0.0,
          "xp_high": 490.0
        },
        "repeating": {
          "accuracy": 0.9999997615814209,
          "confidence": 0.993159830570221,
          "gap": 0.006839931011199951,
          "status": "calibrated",
          "streak": 6150,
          "best_streak": 10495,
          "mastered": true,
          "xp": 640.0,
          "level": 8,
          "level_progress": 0.0,
          "xp_high": 640.0
        },
        "incrementing": {
          "accuracy": 0.9999997615814209,
          "confidence": 0.9814456105232239,
          "gap": 0.01855415105819702,
          "status": "calibrated",
          "streak": 121,
          "best_streak": 727,
          "mastered": true,
          "xp": 640.0,
          "level": 8,
          "level_progress": 0.0,
          "xp_high": 640.0
        },
        "fixed_offset": {
          "accuracy": 0.9240096807479858,
          "confidence": 0.9839407801628113,
          "gap": -0.05993109941482544,
          "status": "calibrated",
          "streak": 3,
          "best_streak": 537,
          "mastered": true,
          "xp": 490.0,
          "level": 7,
          "level_progress": 0.0,
          "xp_high": 490.0
        },
        "periodic_repeat": {
          "accuracy": 0.887822151184082,
          "confidence": 0.8730172514915466,
          "gap": 0.0148048996925354,
          "status": "calibrated",
          "streak": 1,
          "best_streak": 38,
          "mastered": false,
          "xp": 90.0,
          "level": 3,
          "level_progress": 0.0,
          "xp_high": 90.0
        }
      },
      "total_xp": 2350.0,
      "avg_level": 6.599999904632568,
      "exams": [
        {
          "passed": true,
          "score": 0.9375,
          "threshold": 0.85,
          "new_level": 7,
          "xp_lost": 0.0,
          "cooldown": 0,
          "graduated": false,
          "topic": "alternating",
          "target_level": 8
        },
        {
          "passed": true,
          "score": 1.0,
          "threshold": 0.85,
          "new_level": 8,
          "xp_lost": 0.0,
          "cooldown": 0,
          "graduated": false,
          "topic": "repeating",
          "target_level": 9
        },
        {
          "passed": true,
          "score": 1.0,
          "threshold": 0.85,
          "new_level": 8,
          "xp_lost": 0.0,
          "cooldown": 0,
          "graduated": false,
          "topic": "incrementing",
          "target_level": 9
        },
        {
          "passed": true,
          "score": 1.0,
          "threshold": 0.85,
          "new_level": 7,
          "xp_lost": 0.0,
          "cooldown": 0,
          "graduated": false,
          "topic": "fixed_offset",
          "target_level": 8
        },
        {
          "passed": true,
          "score": 1.0,
          "threshold": 0.75,
          "new_level": 3,
          "xp_lost": 0.0,
          "cooldown": 0,
          "graduated": false,
          "topic": "periodic_repeat",
          "target_level": 4
        }
      ]
    },
    {
      "epoch": 9,
      "train_acc": 0.95985,
      "train_loss": 0.12399952122271062,
      "val_acc": 0.9545,
      "show_rate": 0.46125,
      "approval_rate": 1.0,
      "show_reasons": {
        "creative": 8988,
        "streak": 237,
        "validation": 0,
        "spontaneous": 0
      },
      "internalization": 0.9933071732521057,
      "trust": 0.9933071732521057,
      "show_calibration": 0.9999997615814209,
      "per_pattern": {
        "alternating": 0.9472361809045227,
        "repeating": 1.0,
        "incrementing": 0.9668367346938775,
        "fixed_offset": 1.0,
        "periodic_repeat": 0.848404255319149
      },
      "teacher_goal": 36,
      "student_goal_estimate": 35.99998474121094,
      "teacher_impressedness": 1.0,
      "goal_calibration_rate": 0.9501915708812261,
      "topic_calibration": {
        "alternating": {
          "accuracy": 0.9232836365699768,
          "confidence": 0.9676414132118225,
          "gap": -0.0443577766418457,
          "status": "calibrated",
          "streak": 9,
          "best_streak": 114,
          "mastered": true,
          "xp": 640.0,
          "level": 8,
          "level_progress": 0.0,
          "xp_high": 640.0
        },
        "repeating": {
          "accuracy": 0.9999997615814209,
          "confidence": 0.9972001910209656,
          "gap": 0.0027995705604553223,
          "status": "calibrated",
          "streak": 2123,
          "best_streak": 10495,
          "mastered": true,
          "xp": 810.0,
          "level": 9,
          "level_progress": 0.0,
          "xp_high": 810.0
        },
        "incrementing": {
          "accuracy": 0.9998388886451721,
          "confidence": 0.988951563835144,
          "gap": 0.010887324810028076,
          "status": "calibrated",
          "streak": 63,
          "best_streak": 855,
          "mastered": true,
          "xp": 810.0,
          "level": 9,
          "level_progress": 0.0,
          "xp_high": 810.0
        },
        "fixed_offset": {
          "accuracy": 0.9999997615814209,
          "confidence": 0.9874160289764404,
          "gap": 0.012583732604980469,
          "status": "calibrated",
          "streak": 211,
          "best_streak": 537,
          "mastered": true,
          "xp": 640.0,
          "level": 8,
          "level_progress": 0.0,
          "xp_high": 640.0
        },
        "periodic_repeat": {
          "accuracy": 0.8144914507865906,
          "confidence": 0.8722087144851685,
          "gap": -0.05771726369857788,
          "status": "calibrated",
          "streak": 3,
          "best_streak": 38,
          "mastered": false,
          "xp": 160.0,
          "level": 4,
          "level_progress": 0.0,
          "xp_high": 160.0
        }
      },
      "total_xp": 3060.0,
      "avg_level": 7.599999904632568,
      "exams": [
        {
          "passed": true,
          "score": 0.96875,
          "threshold": 0.85,
          "new_level": 8,
          "xp_lost": 0.0,
          "cooldown": 0,
          "graduated": false,
          "topic": "alternating",
          "target_level": 9
        },
        {
          "passed": true,
          "score": 1.0,
          "threshold": 0.85,
          "new_level": 9,
          "xp_lost": 0.0,
          "cooldown": 0,
          "graduated": false,
          "topic": "repeating",
          "target_level": 10
        },
        {
          "passed": true,
          "score": 0.984375,
          "threshold": 0.85,
          "new_level": 9,
          "xp_lost": 0.0,
          "cooldown": 0,
          "graduated": false,
          "topic": "incrementing",
          "target_level": 10
        },
        {
          "passed": true,
          "score": 1.0,
          "threshold": 0.85,
          "new_level": 8,
          "xp_lost": 0.0,
          "cooldown": 0,
          "graduated": false,
          "topic": "fixed_offset",
          "target_level": 9
        },
        {
          "passed": true,
          "score": 0.875,
          "threshold": 0.8,
          "new_level": 4,
          "xp_lost": 0.0,
          "cooldown": 0,
          "graduated": false,
          "topic": "periodic_repeat",
          "target_level": 5
        }
      ]
    },
    {
      "epoch": 10,
      "train_acc": 0.9644,
      "train_loss": 0.10794955684542656,
      "val_acc": 0.9675,
      "show_rate": 0.4373,
      "approval_rate": 1.0,
      "show_reasons": {
        "creative": 8485,
        "streak": 261,
        "validation": 0,
        "spontaneous": 0
      },
      "internalization": 0.9933071732521057,
      "trust": 0.9933071732521057,
      "show_calibration": 0.9999997615814209,
      "per_pattern": {
        "alternating": 0.9723618090452262,
        "repeating": 1.0,
        "incrementing": 1.0,
        "fixed_offset": 0.9951573849878934,
        "periodic_repeat": 0.8617021276595744
      },
      "teacher_goal": 36,
      "student_goal_estimate": 35.99998474121094,
      "teacher_impressedness": 1.0,
      "goal_calibration_rate": 0.9626436781609196,
      "topic_calibration": {
        "alternating": {
          "accuracy": 0.8971982598304749,
          "confidence": 0.9519138336181641,
          "gap": -0.05471557378768921,
          "status": "calibrated",
          "streak": 0,
          "best_streak": 183,
          "mastered": true,
          "xp": 810.0,
          "level": 9,
          "level_progress": 0.0,
          "xp_high": 810.0
        },
        "repeating": {
          "accuracy": 0.9999997615814209,
          "confidence": 0.9967791438102722,
          "gap": 0.0032206177711486816,
          "status": "calibrated",
          "streak": 6116,
          "best_streak": 10495,
          "mastered": true,
          "xp": 1000.0,
          "level": 10,
          "level_progress": 1.0,
          "xp_high": 1000.0
        },
        "incrementing": {
          "accuracy": 0.9996077418327332,
          "confidence": 0.977008581161499,
          "gap": 0.02259916067123413,
          "status": "calibrated",
          "streak": 53,
          "best_streak": 964,
          "mastered": true,
          "xp": 1000.0,
          "level": 10,
          "level_progress": 1.0,
          "xp_high": 1000.0
        },
        "fixed_offset": {
          "accuracy": 0.9996957182884216,
          "confidence": 0.9719479084014893,
          "gap": 0.027747809886932373,
          "status": "calibrated",
          "streak": 55,
          "best_streak": 537,
          "mastered": true,
          "xp": 810.0,
          "level": 9,
          "level_progress": 0.0,
          "xp_high": 810.0
        },
        "periodic_repeat": {
          "accuracy": 0.9135509133338928,
          "confidence": 0.8476436138153076,
          "gap": 0.0659072995185852,
          "status": "calibrated",
          "streak": 15,
          "best_streak": 43,
          "mastered": false,
          "xp": 250.0,
          "level": 5,
          "level_progress": 0.0,
          "xp_high": 250.0
        }
      },
      "total_xp": 3870.0,
      "avg_level": 8.600000381469727,
      "exams": [
        {
          "passed": true,
          "score": 0.984375,
          "threshold": 0.85,
          "new_level": 9,
          "xp_lost": 0.0,
          "cooldown": 0,
          "graduated": false,
          "topic": "alternating",
          "target_level": 10
        },
        {
          "passed": true,
          "score": 1.0,
          "threshold": 0.9,
          "new_level": 10,
          "xp_lost": 0.0,
          "cooldown": 0,
          "graduated": true,
          "topic": "repeating",
          "target_level": 11
        },
        {
          "passed": true,
          "score": 1.0,
          "threshold": 0.9,
          "new_level": 10,
          "xp_lost": 0.0,
          "cooldown": 0,
          "graduated": true,
          "topic": "incrementing",
          "target_level": 11
        },
        {
          "passed": true,
          "score": 0.984375,
          "threshold": 0.85,
          "new_level": 9,
          "xp_lost": 0.0,
          "cooldown": 0,
          "graduated": false,
          "topic": "fixed_offset",
          "target_level": 10
        },
        {
          "passed": false,
          "score": 0.6875,
          "threshold": 0.8,
          "new_level": 4,
          "xp_lost": 22.5,
          "cooldown": 5,
          "graduated": false,
          "topic": "periodic_repeat",
          "target_level": 6
        }
      ]
    }
  ]
}